pm/__init__.py
pm/db.py
pm/main.py
pm/password.py
SecureO-0.9.dist-info/METADATA
SecureO-0.9.dist-info/WHEEL
SecureO-0.9.dist-info/entry_points.txt
SecureO-0.9.dist-info/top_level.txt
SecureO-0.9.dist-info/RECORD
