Metadata-Version: 2.1
Name: SecureO
Version: 0.9
Summary: A command-line password manager
Home-page: https://github.com/yash-k-jain/password-manager
Author: Yash Jain
Author-email: yash.test.project@gmail.com
Classifier: Programming Language :: Python :: 3
Classifier: License :: OSI Approved :: MIT License
Classifier: Operating System :: OS Independent
Requires-Python: >=3.6
Requires-Dist: pymongo
Requires-Dist: bcrypt
Requires-Dist: tabulate
